Workbook

Sheet Инструкция
A1: LEGITIMUS · Partner Rate Card: ЧЕРНОВИК СТРУКТУРЫ для утверждения управляющим партнёром
A2: Тарифы НЕ заполнены намеренно: агент не придумывает цены. Все ЖЁЛТЫЕ ячейки заполняет и утверждает управляющий партнёр (синий шрифт = вводимые данные).
A3: Как заполнять: 1) лист «Параметры»: валюта, базовая скидка, часовые ставки, условия; 2) лист «Rate Card»: стандартная ставка (столбец H) и, при необходимости, индивидуальная партнёрская ставка (I). Расчётная партнёрская ставка (J) и скидка (K) считаются автоматически; 3) столбец «Утверждено» = Да/Нет.
A4: Пример формата: строка RC-01, стандартная ставка 0 (заменить реальной суммой), срок «[TO CONFIRM]», утверждено «Нет».
A5: Государственные пошлины, нотариальные расходы, переводы и апостили: перевыставляются по фактическим затратам (pass-through), в ставки не включаются, если не утверждено иное.
A6: Этика: реферальные вознаграждения, раздел гонорара и white-label требуют заключения о допустимости (лист «Этика и механика»). До этого Rate Card используется только для прямого договора с клиентом или с партнёрской скидкой.
A7: Услуги MyAccounting оказывает отдельное лицо; его ставки утверждаются по договору с MyAccounting [TO CONFIRM].

Sheet Rate Card
A1: Код | B1: Категория | C1: Услуга | D1: Что включено (scope) | E1: Не включено / pass-through | F1: Исполнитель | G1: Единица | H1: Стандартная ставка | I1: Партнёрская ставка (индивид.) | J1: Расчётная партнёрская ставка | K1: Скидка партнёру | L1: Ориентировочный срок | M1: Модели | N1: Флаг этики / подтверждения | O1: Утверждено | P1: Комментарий MP
A2: 1. Регистрация компании
A3: RC-01 | B3: Регистрация компании | C3: Регистрация SRL (учредители — физ. лица) | D3: Консультация по структуре, устав, документы, подача в ASP [TO CONFIRM процесс], получение документов о регистрации | E3: Госпошлины, нотариус, переводы, апостиль | F3: LEGITIMUS | G3: за компанию | H3: 0 | J3: =IF(H3="","",IF(I3<>"",I3,H3*(1-Параметры!$B$3))) -> 0 | K3: =IF(OR(H3="",H3=0),"",1-J3/H3) | L3: [TO CONFIRM] | M3: A,B | O3: Нет
A4: RC-02 | B4: Регистрация компании | C4: Регистрация SRL с иностранным юр. лицом-учредителем | D4: То же + проверка корпоративных документов иностранного учредителя и требований к легализации | E4: Легализация/апостиль, переводы | F4: LEGITIMUS | G4: за компанию | J4: =IF(H4="","",IF(I4<>"",I4,H4*(1-Параметры!$B$3))) | K4: =IF(OR(H4="",H4=0),"",1-J4/H4) | L4: [TO CONFIRM] | M4: A,B
A5: RC-03 | B5: Регистрация компании | C5: Регистрация филиала / представительства иностранной компании | D5: Документы, положение о филиале, регистрация [TO CONFIRM] | E5: Госпошлины, переводы | F5: LEGITIMUS | G5: за подразделение | J5: =IF(H5="","",IF(I5<>"",I5,H5*(1-Параметры!$B$3))) | K5: =IF(OR(H5="",H5=0),"",1-J5/H5) | L5: [TO CONFIRM] | M5: A,B,C | N5: Подтвердить, что LEGITIMUS оказывает эту услугу
A6: RC-04 | B6: Регистрация компании | C6: Регистрация плательщика НДС и иная налоговая регистрация | D6: Подготовка и подача заявлений [TO CONFIRM] | E6: — | F6: MyAccounting / LEGITIMUS | G6: за регистрацию | J6: =IF(H6="","",IF(I6<>"",I6,H6*(1-Параметры!$B$3))) | K6: =IF(OR(H6="",H6=0),"",1-J6/H6) | L6: [TO CONFIRM] | M6: A,B | N6: Разграничить исполнителя: LEGITIMUS или MyAccounting
A7: RC-05 | B7: Регистрация компании | C7: Содействие в открытии банковского счёта | D7: Подготовка пакета документов, сопровождение; результат не гарантируется | E7: Комиссии банка | F7: LEGITIMUS | G7: за счёт | J7: =IF(H7="","",IF(I7<>"",I7,H7*(1-Параметры!$B$3))) | K7: =IF(OR(H7="",H7=0),"",1-J7/H7) | L7: [TO CONFIRM] | M7: A,B | N7: Не обещать открытие счёта
A8: 2. Корпоративные изменения
A9: RC-06 | B9: Корпоративные изменения | C9: Смена администратора (директора) | D9: Решения, документы, регистрация изменений | E9: Госпошлины, нотариус | F9: LEGITIMUS | G9: за изменение | J9: =IF(H9="","",IF(I9<>"",I9,H9*(1-Параметры!$B$3))) | K9: =IF(OR(H9="",H9=0),"",1-J9/H9) | L9: [TO CONFIRM] | M9: A,B,C
A10: RC-07 | B10: Корпоративные изменения | C10: Передача долей / смена участников | D10: Договор, решения, регистрация | E10: Госпошлины, нотариус | F10: LEGITIMUS | G10: за сделку | J10: =IF(H10="","",IF(I10<>"",I10,H10*(1-Параметры!$B$3))) | K10: =IF(OR(H10="",H10=0),"",1-J10/H10) | L10: [TO CONFIRM] | M10: A,B,C
A11: RC-08 | B11: Корпоративные изменения | C11: Изменение устава / вида деятельности / адреса | D11: Документы и регистрация изменений | E11: Госпошлины | F11: LEGITIMUS | G11: за изменение | J11: =IF(H11="","",IF(I11<>"",I11,H11*(1-Параметры!$B$3))) | K11: =IF(OR(H11="",H11=0),"",1-J11/H11) | L11: [TO CONFIRM] | M11: A,B,C
A12: RC-09 | B12: Корпоративные изменения | C12: Увеличение / уменьшение уставного капитала | D12: Документы, регистрация | E12: Госпошлины | F12: LEGITIMUS | G12: за изменение | J12: =IF(H12="","",IF(I12<>"",I12,H12*(1-Параметры!$B$3))) | K12: =IF(OR(H12="",H12=0),"",1-J12/H12) | L12: [TO CONFIRM] | M12: A,B,C
A13: RC-10 | B13: Корпоративные изменения | C13: Обновление сведений о бенефициарах | D13: Подготовка и подача сведений [TO CONFIRM требования] | E13: — | F13: LEGITIMUS | G13: за обновление | J13: =IF(H13="","",IF(I13<>"",I13,H13*(1-Параметры!$B$3))) | K13: =IF(OR(H13="",H13=0),"",1-J13/H13) | L13: [TO CONFIRM] | M13: A,B,C
A14: RC-11 | B14: Корпоративные изменения | C14: Добровольная ликвидация | D14: Процедура «под ключ» [TO CONFIRM объём] | E14: Госпошлины, публикации | F14: LEGITIMUS | G14: за процедуру | J14: =IF(H14="","",IF(I14<>"",I14,H14*(1-Параметры!$B$3))) | K14: =IF(OR(H14="",H14=0),"",1-J14/H14) | L14: [TO CONFIRM] | M14: A,B,C
A15: 3. Юридический адрес
A16: RC-12 | B16: Юридический адрес | C16: Предоставление юридического адреса | D16: Адрес для регистрации [TO CONFIRM правомерность и наличие помещений] | E16: — | F16: LEGITIMUS | G16: в год | J16: =IF(H16="","",IF(I16<>"",I16,H16*(1-Параметры!$B$3))) | K16: =IF(OR(H16="",H16=0),"",1-J16/H16) | L16: [TO CONFIRM] | M16: A,B | N16: Подтвердить, может ли LEGITIMUS законно предоставлять адрес
A17: RC-13 | B17: Юридический адрес | C17: Приём и пересылка корреспонденции | D17: Скан входящей почты, уведомления | E17: Курьерские расходы | F17: LEGITIMUS | G17: в месяц | J17: =IF(H17="","",IF(I17<>"",I17,H17*(1-Параметры!$B$3))) | K17: =IF(OR(H17="",H17=0),"",1-J17/H17) | L17: [TO CONFIRM] | M17: A,B
A18: 4. Корпоративное администрирование
A19: RC-14 | B19: Корпоративное администрирование | C19: Годовой пакет корпоративного обслуживания | D19: Годовое собрание или решения участника, протоколы, ведение корпоративных документов | E19: — | F19: LEGITIMUS | G19: в год | J19: =IF(H19="","",IF(I19<>"",I19,H19*(1-Параметры!$B$3))) | K19: =IF(OR(H19="",H19=0),"",1-J19/H19) | L19: [TO CONFIRM] | M19: A,B,C
A20: RC-15 | B20: Корпоративное администрирование | C20: Решения и протоколы по запросу | D20: Подготовка отдельных корпоративных документов | E20: — | F20: LEGITIMUS | G20: за документ | J20: =IF(H20="","",IF(I20<>"",I20,H20*(1-Параметры!$B$3))) | K20: =IF(OR(H20="",H20=0),"",1-J20/H20) | L20: [TO CONFIRM] | M20: A,B,C
A21: RC-16 | B21: Корпоративное администрирование | C21: Корпоративный секретарь / контроль сроков | D21: Календарь корпоративных сроков и напоминания [TO CONFIRM] | E21: — | F21: LEGITIMUS | G21: в месяц | J21: =IF(H21="","",IF(I21<>"",I21,H21*(1-Параметры!$B$3))) | K21: =IF(OR(H21="",H21=0),"",1-J21/H21) | L21: [TO CONFIRM] | M21: B,C
A22: 5. Ежемесячное юридическое сопровождение
A23: RC-17 | B23: Ежемесячное юридическое сопровождение | C23: Пакет Basic | D23: [N] часов в месяц: консультации, проверка документов | E23: Судебное представительство | F23: LEGITIMUS | G23: в месяц | J23: =IF(H23="","",IF(I23<>"",I23,H23*(1-Параметры!$B$3))) | K23: =IF(OR(H23="",H23=0),"",1-J23/H23) | L23: [TO CONFIRM] | M23: C | N23: Указать число часов
A24: RC-18 | B24: Ежемесячное юридическое сопровождение | C24: Пакет Standard | D24: [N] часов в месяц + приоритетный срок ответа [TO AGREE SLA] | E24: Судебное представительство | F24: LEGITIMUS | G24: в месяц | J24: =IF(H24="","",IF(I24<>"",I24,H24*(1-Параметры!$B$3))) | K24: =IF(OR(H24="",H24=0),"",1-J24/H24) | L24: [TO CONFIRM] | M24: C
A25: RC-19 | B25: Ежемесячное юридическое сопровождение | C25: Пакет Premium | D25: [N] часов в месяц + выделенный юрист | E25: — | F25: LEGITIMUS | G25: в месяц | J25: =IF(H25="","",IF(I25<>"",I25,H25*(1-Параметры!$B$3))) | K25: =IF(OR(H25="",H25=0),"",1-J25/H25) | L25: [TO CONFIRM] | M25: C
A26: RC-20 | B26: Ежемесячное юридическое сопровождение | C26: Часы сверх пакета | D26: По часовой ставке (лист «Параметры») | E26: — | F26: LEGITIMUS | G26: час | J26: =IF(H26="","",IF(I26<>"",I26,H26*(1-Параметры!$B$3))) | K26: =IF(OR(H26="",H26=0),"",1-J26/H26) | L26: [TO CONFIRM] | M26: A,B,C
A27: 6. Бухгалтерское обслуживание (MyAccounting)
A28: RC-21 | B28: Бухгалтерское обслуживание (MyAccounting) | C28: Бухгалтерский учёт: компания без операций | D28: Ведение учёта и отчётность [TO CONFIRM] | E28: — | F28: MyAccounting | G28: в месяц | J28: =IF(H28="","",IF(I28<>"",I28,H28*(1-Параметры!$B$3))) | K28: =IF(OR(H28="",H28=0),"",1-J28/H28) | L28: [TO CONFIRM] | M28: A,B,C | N28: Договор с MyAccounting; кто выставляет счёт
A29: RC-22 | B29: Бухгалтерское обслуживание (MyAccounting) | C29: Бухгалтерский учёт: до [N] операций в месяц | D29: Учёт, налоговая отчётность | E29: — | F29: MyAccounting | G29: в месяц | J29: =IF(H29="","",IF(I29<>"",I29,H29*(1-Параметры!$B$3))) | K29: =IF(OR(H29="",H29=0),"",1-J29/H29) | L29: [TO CONFIRM] | M29: A,B,C
A30: RC-23 | B30: Бухгалтерское обслуживание (MyAccounting) | C30: Расчёт зарплаты | D30: Расчёт зарплаты и отчётность по работникам | E30: — | F30: MyAccounting | G30: за работника в месяц | J30: =IF(H30="","",IF(I30<>"",I30,H30*(1-Параметры!$B$3))) | K30: =IF(OR(H30="",H30=0),"",1-J30/H30) | L30: [TO CONFIRM] | M30: A,B,C
A31: RC-24 | B31: Бухгалтерское обслуживание (MyAccounting) | C31: Годовая финансовая отчётность | D31: Подготовка и подача [TO CONFIRM] | E31: Аудит, если обязателен | F31: MyAccounting | G31: в год | J31: =IF(H31="","",IF(I31<>"",I31,H31*(1-Параметры!$B$3))) | K31: =IF(OR(H31="",H31=0),"",1-J31/H31) | L31: [TO CONFIRM] | M31: A,B,C
A32: 7. Дополнительные юридические услуги
A33: RC-25 | B33: Дополнительные юридические услуги | C33: Правовое заключение (правоспособность, good standing) | D33: Заключение адвоката на английском [TO CONFIRM языки] | E33: — | F33: LEGITIMUS | G33: за заключение | J33: =IF(H33="","",IF(I33<>"",I33,H33*(1-Параметры!$B$3))) | K33: =IF(OR(H33="",H33=0),"",1-J33/H33) | L33: [TO CONFIRM] | M33: B,C
A34: RC-26 | B34: Дополнительные юридические услуги | C34: Подготовка / проверка коммерческого договора | D34: Договор на английском, румынском или русском [TO CONFIRM] | E34: Переводы | F34: LEGITIMUS | G34: за договор / час | J34: =IF(H34="","",IF(I34<>"",I34,H34*(1-Параметры!$B$3))) | K34: =IF(OR(H34="",H34=0),"",1-J34/H34) | L34: [TO CONFIRM] | M34: A,B,C
A35: RC-27 | B35: Дополнительные юридические услуги | C35: Трудовые документы (пакет для работодателя) | D35: Трудовые договоры, внутренние положения | E35: — | F35: LEGITIMUS | G35: пакет | J35: =IF(H35="","",IF(I35<>"",I35,H35*(1-Параметры!$B$3))) | K35: =IF(OR(H35="",H35=0),"",1-J35/H35) | L35: [TO CONFIRM] | M35: A,B,C
A36: RC-28 | B36: Дополнительные юридические услуги | C36: Разрешения на работу и проживание для иностранцев | D36: Сопровождение процедуры [TO CONFIRM, что LEGITIMUS оказывает] | E36: Госпошлины | F36: LEGITIMUS | G36: за человека | J36: =IF(H36="","",IF(I36<>"",I36,H36*(1-Параметры!$B$3))) | K36: =IF(OR(H36="",H36=0),"",1-J36/H36) | L36: [TO CONFIRM] | M36: A,B,C | N36: Не обещать результат
A37: RC-29 | B37: Дополнительные юридические услуги | C37: Защита данных: аудит соответствия Закону 195/2024 | D37: Аудит, политики, реестры [TO CONFIRM объём] | E37: — | F37: LEGITIMUS | G37: проект | J37: =IF(H37="","",IF(I37<>"",I37,H37*(1-Параметры!$B$3))) | K37: =IF(OR(H37="",H37=0),"",1-J37/H37) | L37: [TO CONFIRM] | M37: B,C
A38: RC-30 | B38: Дополнительные юридические услуги | C38: Юридическая проверка (due diligence) | D38: Проверка компании или актива | E38: — | F38: LEGITIMUS | G38: проект / час | J38: =IF(H38="","",IF(I38<>"",I38,H38*(1-Параметры!$B$3))) | K38: =IF(OR(H38="",H38=0),"",1-J38/H38) | L38: [TO CONFIRM] | M38: C
A39: RC-31 | B39: Дополнительные юридические услуги | C39: Сопровождение сделки M&A / инвестиции | D39: Структура, документы, закрытие [TO CONFIRM опыт и объём] | E39: — | F39: LEGITIMUS | G39: проект / час | J39: =IF(H39="","",IF(I39<>"",I39,H39*(1-Параметры!$B$3))) | K39: =IF(OR(H39="",H39=0),"",1-J39/H39) | L39: [TO CONFIRM] | M39: C
A40: RC-32 | B40: Дополнительные юридические услуги | C40: Лицензирование и регуляторные вопросы | D40: По отраслям [TO CONFIRM] | E40: Госпошлины | F40: LEGITIMUS | G40: проект | J40: =IF(H40="","",IF(I40<>"",I40,H40*(1-Параметры!$B$3))) | K40: =IF(OR(H40="",H40=0),"",1-J40/H40) | L40: [TO CONFIRM] | M40: A,B,C

Sheet Параметры
A1: Параметр | B1: Значение | C1: Комментарий
A2: Валюта тарифов | B2: EUR | C2: [TO CONFIRM] EUR или MDL; при MDL указать курс и порядок пересчёта
A3: Базовая партнёрская скидка (доля) | C3: Например 0.10 = 10%. Применяется, если индивидуальная партнёрская ставка не задана
A4: Стандартная часовая ставка, старший юрист / партнёр | C4: Для работ сверх пакетов
A5: Стандартная часовая ставка, юрист
A6: Партнёрская часовая ставка, юрист
A7: НДС и налоги на гонорар | C7: [TO CONFIRM] режим налогообложения гонорара адвоката
A8: Условия оплаты | C8: Например: предоплата за регистрацию, ежемесячно за пакеты
A9: Срок действия Rate Card | C9: Дата пересмотра
A10: Минимальный ежемесячный пакет (Model C)
A11: Порог объёма для дополнительной скидки (заявок в год)

Sheet Статус заполнения
A1: Категория | B1: Строк | C1: Заполнена стандартная ставка | D1: Утверждено | E1: Готовность
A2: Регистрация компании | B2: =COUNTIF('Rate Card'!$B$3:$B$40,A2) -> 5 | C2: =COUNTIFS('Rate Card'!$B$3:$B$40,A2,'Rate Card'!$H$3:$H$40,">0") -> 0 | D2: =COUNTIFS('Rate Card'!$B$3:$B$40,A2,'Rate Card'!$O$3:$O$40,"Да") -> 0 | E2: =IF(B2=0,"",D2/B2) -> 0
A3: Корпоративные изменения | B3: =COUNTIF('Rate Card'!$B$3:$B$40,A3) -> 6 | C3: =COUNTIFS('Rate Card'!$B$3:$B$40,A3,'Rate Card'!$H$3:$H$40,">0") -> 0 | D3: =COUNTIFS('Rate Card'!$B$3:$B$40,A3,'Rate Card'!$O$3:$O$40,"Да") -> 0 | E3: =IF(B3=0,"",D3/B3) -> 0
A4: Юридический адрес | B4: =COUNTIF('Rate Card'!$B$3:$B$40,A4) -> 2 | C4: =COUNTIFS('Rate Card'!$B$3:$B$40,A4,'Rate Card'!$H$3:$H$40,">0") -> 0 | D4: =COUNTIFS('Rate Card'!$B$3:$B$40,A4,'Rate Card'!$O$3:$O$40,"Да") -> 0 | E4: =IF(B4=0,"",D4/B4) -> 0
A5: Корпоративное администрирование | B5: =COUNTIF('Rate Card'!$B$3:$B$40,A5) -> 3 | C5: =COUNTIFS('Rate Card'!$B$3:$B$40,A5,'Rate Card'!$H$3:$H$40,">0") -> 0 | D5: =COUNTIFS('Rate Card'!$B$3:$B$40,A5,'Rate Card'!$O$3:$O$40,"Да") -> 0 | E5: =IF(B5=0,"",D5/B5) -> 0
A6: Ежемесячное юридическое сопровождение | B6: =COUNTIF('Rate Card'!$B$3:$B$40,A6) -> 4 | C6: =COUNTIFS('Rate Card'!$B$3:$B$40,A6,'Rate Card'!$H$3:$H$40,">0") -> 0 | D6: =COUNTIFS('Rate Card'!$B$3:$B$40,A6,'Rate Card'!$O$3:$O$40,"Да") -> 0 | E6: =IF(B6=0,"",D6/B6) -> 0
A7: Бухгалтерское обслуживание (MyAccounting) | B7: =COUNTIF('Rate Card'!$B$3:$B$40,A7) -> 4 | C7: =COUNTIFS('Rate Card'!$B$3:$B$40,A7,'Rate Card'!$H$3:$H$40,">0") -> 0 | D7: =COUNTIFS('Rate Card'!$B$3:$B$40,A7,'Rate Card'!$O$3:$O$40,"Да") -> 0 | E7: =IF(B7=0,"",D7/B7) -> 0
A8: Дополнительные юридические услуги | B8: =COUNTIF('Rate Card'!$B$3:$B$40,A8) -> 8 | C8: =COUNTIFS('Rate Card'!$B$3:$B$40,A8,'Rate Card'!$H$3:$H$40,">0") -> 0 | D8: =COUNTIFS('Rate Card'!$B$3:$B$40,A8,'Rate Card'!$O$3:$O$40,"Да") -> 0 | E8: =IF(B8=0,"",D8/B8) -> 0
A9: Итого | B9: =SUM(B2:B8) -> 32 | C9: =SUM(C2:C8) -> 0 | D9: =SUM(D2:D8) -> 0 | E9: =IF(B9=0,"",D9/B9) -> 0

Sheet Этика и механика
A1: Механизм | B1: Описание | C1: Риск / вопрос | D1: Статус | E1: Решение MP
A2: Прямой договор с клиентом + партнёрская скидка | B2: Партнёр рекомендует, клиент заключает договор с LEGITIMUS; партнёр не получает вознаграждения | C2: Наименьший риск; нужна прозрачность для клиента | D2: Рекомендуемая базовая модель
A3: Субподряд (white-label) | B3: Партнёр заключает договор с клиентом и привлекает LEGITIMUS как исполнителя | C3: Адвокатская тайна, ответственность перед конечным клиентом, конфликт интересов, KYC конечного клиента; допустимость по Закону об адвокатуре и Кодексу этики | D3: ТРЕБУЕТ ЗАКЛЮЧЕНИЯ
A4: Реферальное вознаграждение партнёру | B4: LEGITIMUS платит партнёру за рекомендацию клиента (пример: Commitbiz публикует 20%) | C4: Раздел гонорара с неадвокатами и плата за привлечение клиентов могут быть ограничены; специальная норма в открытых источниках не найдена | D4: ТРЕБУЕТ ЗАКЛЮЧЕНИЯ
A5: Получение вознаграждения от партнёра | B5: LEGITIMUS рекомендует клиента партнёру (например, в ОАЭ) и получает вознаграждение | C5: Конфликт интересов и обязанность раскрыть клиенту; допустимость по Кодексу этики | D5: ТРЕБУЕТ ЗАКЛЮЧЕНИЯ
A6: Связка с MyAccounting | B6: Совместное предложение юридических и бухгалтерских услуг | C6: Раздельные договоры и ответственность; раскрытие связи клиенту; обмен данными (Закон 195/2024) | D6: [TO CONFIRM]
A8: Источник по общим нормам о гонораре: https://crjm.org/wp-content/uploads/2002/12/Codul-deontologic-avocati.pdf (Кодекс этики адвоката РМ). Специальная норма о разделе гонорара не найдена: нужна проверка полного текста или запрос в Союз адвокатов.
